azure/mgmt/resource/bicep/__init__.py
azure/mgmt/resource/bicep/_client.py
azure/mgmt/resource/bicep/_configuration.py
azure/mgmt/resource/bicep/_patch.py
azure/mgmt/resource/bicep/_version.py
azure/mgmt/resource/bicep/py.typed
azure/mgmt/resource/bicep/_utils/__init__.py
azure/mgmt/resource/bicep/_utils/model_base.py
azure/mgmt/resource/bicep/_utils/serialization.py
azure/mgmt/resource/bicep/aio/__init__.py
azure/mgmt/resource/bicep/aio/_client.py
azure/mgmt/resource/bicep/aio/_configuration.py
azure/mgmt/resource/bicep/aio/_patch.py
azure/mgmt/resource/bicep/aio/operations/__init__.py
azure/mgmt/resource/bicep/aio/operations/_operations.py
azure/mgmt/resource/bicep/aio/operations/_patch.py
azure/mgmt/resource/bicep/models/__init__.py
azure/mgmt/resource/bicep/models/_models.py
azure/mgmt/resource/bicep/models/_patch.py
azure/mgmt/resource/bicep/operations/__init__.py
azure/mgmt/resource/bicep/operations/_operations.py
azure/mgmt/resource/bicep/operations/_patch.py
azure_mgmt_resource_bicep-1.0.0b1.dist-info/LICENSE
azure_mgmt_resource_bicep-1.0.0b1.dist-info/METADATA
azure_mgmt_resource_bicep-1.0.0b1.dist-info/WHEEL
azure_mgmt_resource_bicep-1.0.0b1.dist-info/top_level.txt
azure_mgmt_resource_bicep-1.0.0b1.dist-info/RECORD
